Lab4a/fsm_bspd_other_method.v
// Serial Input BitStream Pattern Detector
module fsm_bspd(clk, reset, bit_in, det_out);
input 	clk, reset, bit_in;
output 	det_out;

//not finite state machine method

reg [3:0] temp;
always@(posedge clk)
begin
    if(reset)
        temp <= 3'd0;
    else
    begin
        //mem[0] <= bit_in;
        temp[1] <= temp[0];
        temp[2] <= temp[1];
        temp[3] <= temp[2];
    end
end

always@(*)
begin
    temp[0] = bit_in;
end
assign det_out = (temp == 4'b0010)? 1: 0; 

endmodule

Lab4a/fsm_test.v
//*****************************************************
// Testbench for the Serial Input Bitstream Pattern Detector
//*****************************************************

`timescale 1ns/10ps

module test_fsm;

`define CYCLE 10

reg clk;
reg reset, EN, bit_in;
reg answer;
integer count;
reg [3:0] cnt;
reg [4:0] shifter;
reg [9:0] data;
reg [31:0] cycle;

parameter [2:0] A0=3'b000, A1=3'b001,A2=3'b010,A3=3'b011,A4=3'b100;


//////////////////////////////////////////////////////
// DUT instance
//////////////////////////////////////////////////////
fsm_bspd i_fsm(.clk(clk), .reset(reset), .bit_in(bit_in), .det_out(det_out));


//////////////////////////////////////////////////////
// clock gen.
//////////////////////////////////////////////////////
initial clk = 0;
always #(`CYCLE/2 ) clk = ~clk;


//////////////////////////////////////////////////////
// initial setup & Finish flag
//////////////////////////////////////////////////////
initial
begin
	reset = 1'b1;
	EN = 1'b1;
	bit_in = 1'b0;
	answer = 1'b0;
	#13  reset = 1'b0;
	#4000
	$display("************************************************************"); 
	$display($time, ,"Finish testing with no error");
	$display("************************************************************"); 
	$finish;
end

//////////////////////////////////////////////////////
// stimulus gen.
//////////////////////////////////////////////////////

always@(posedge clk)
begin
if (reset) cnt <=  9;  // count the bit of data to be input
else  begin
	if (cnt == 0)  cnt <=  9;
	else cnt <=  cnt -1 ;
end
end


always@(posedge clk)
begin
if (reset) data <= 0;  
else if (cnt == 0) data <= data + 1;
else data <= data;
end




always@(posedge clk)
begin
if (reset) shifter <=   5'bxxxxx; // store value of data stream, used to generate golden pattern
else  begin
	shifter[4:1] <=  shifter [3:0];
	shifter[0] <=  data[cnt];
end
end

always@(posedge clk)
begin
if (reset) bit_in <=  0;
else bit_in <=  data[cnt];
end

always@(shifter or count)
begin
if (!shifter[3] && !shifter[2] && shifter[1] && !shifter[0])  answer = 1;
else answer = 0;
end



always@(posedge clk)
begin
if (reset) cycle <= 0;
else cycle <= cycle + 1;
#(`CYCLE/5) 
if (det_out == answer) begin
	
	end
else  begin
		$display($time,,"Testing failed at cycle %d !!, det_out should be %b", cycle, answer);
		#(`CYCLE * 2)
		$finish;
		end
end

//////////////////////////////////////////////////////
// Waveform DataBase.
//////////////////////////////////////////////////////
initial
begin
//$fsdbDumpfile("fsm_wave.fsdb");
//$fsdbDumpvars();
$dumpfile("fsm_wave.vcd");
$dumpvars;
end


endmodule

Lab4a/fsm_wave.vcd
$date
	Wed Jan 17 23:38:36 2024
$end
$version
	Icarus Verilog
$end
$timescale
	10ps
$end
$scope module test_fsm $end
$var wire 1 ! det_out $end
$var parameter 3 " A0 $end
$var parameter 3 # A1 $end
$var parameter 3 $ A2 $end
$var parameter 3 % A3 $end
$var parameter 3 & A4 $end
$var reg 1 ' EN $end
$var reg 1 ( answer $end
$var reg 1 ) bit_in $end
$var reg 1 * clk $end
$var reg 4 + cnt [3:0] $end
$var reg 32 , cycle [31:0] $end
$var reg 10 - data [9:0] $end
$var reg 1 . reset $end
$var reg 5 / shifter [4:0] $end
$var integer 32 0 count [31:0] $end
$scope module i_fsm $end
$var wire 1 ) bit_in $end
$var wire 1 * clk $end
$var wire 1 . reset $end
$var wire 1 ! det_out $end
$var reg 4 1 temp [3:0] $end
$upscope $end
$upscope $end
$enddefinitions $end
$comment Show the parameter values. $end
$dumpall
b100 &
b11 %
b10 $
b1 #
b0 "
$end
#0
$dumpvars
bx0 1
bx 0
bx /
1.
bx -
bx ,
bx +
0*
0)
0(
1'
x!
$end
#500
0!
b0 1
b1001 +
b0 -
b0 ,
1*
#1000
0*
#1300
0.
#1500
bx0 /
b1000 +
b1 ,
1*
#2000
0*
#2500
b111 +
bx00 /
b10 ,
1*
#3000
0*
#3500
bx000 /
b110 +
b11 ,
1*
#4000
0*
#4500
b101 +
bx0000 /
b100 ,
1*
#5000
0*
#5500
b0 /
b100 +
b101 ,
1*
#6000
0*
#6500
b11 +
b110 ,
1*
#7000
0*
#7500
b10 +
b111 ,
1*
#8000
0*
#8500
b1 +
b1000 ,
1*
#9000
0*
#9500
b0 +
b1001 ,
1*
#10000
0*
#10500
b1001 +
b1 -
b1010 ,
1*
#11000
0*
#11500
b1000 +
b1011 ,
1*
#12000
0*
#12500
b111 +
b1100 ,
1*
#13000
0*
#13500
b110 +
b1101 ,
1*
#14000
0*
#14500
b101 +
b1110 ,
1*
#15000
0*
#15500
b100 +
b1111 ,
1*
#16000
0*
#16500
b11 +
b10000 ,
1*
#17000
0*
#17500
b10 +
b10001 ,
1*
#18000
0*
#18500
b1 +
b10010 ,
1*
#19000
0*
#19500
b0 +
b10011 ,
1*
#20000
0*
#20500
b1 1
b1001 +
b10 -
b1 /
1)
b10100 ,
1*
#21000
0*
#21500
1!
1(
0)
b10 /
b1000 +
b10 1
b10101 ,
1*
#22000
0*
#22500
0!
0(
b100 1
b111 +
b100 /
b10110 ,
1*
#23000
0*
#23500
b1000 /
b110 +
b1000 1
b10111 ,
1*
#24000
0*
#24500
b0 1
b101 +
b10000 /
b11000 ,
1*
#25000
0*
#25500
b0 /
b100 +
b11001 ,
1*
#26000
0*
#26500
b11 +
b11010 ,
1*
#27000
0*
#27500
b10 +
b11011 ,
1*
#28000
0*
#28500
b1 +
b11100 ,
1*
#29000
0*
#29500
b1 1
1)
b1 /
b0 +
b11101 ,
1*
#30000
0*
#30500
1!
1(
b10 1
b1001 +
b11 -
b10 /
0)
b11110 ,
1*
#31000
0*
#31500
0!
0(
b100 /
b1000 +
b100 1
b11111 ,
1*
#32000
0*
#32500
b1000 1
b111 +
b1000 /
b100000 ,
1*
#33000
0*
#33500
b10000 /
b110 +
b0 1
b100001 ,
1*
#34000
0*
#34500
b101 +
b0 /
b100010 ,
1*
#35000
0*
#35500
b100 +
b100011 ,
1*
#36000
0*
#36500
b11 +
b100100 ,
1*
#37000
0*
#37500
b10 +
b100101 ,
1*
#38000
0*
#38500
b1 +
b100110 ,
1*
#39000
0*
#39500
b1 1
1)
b1 /
b0 +
b100111 ,
1*
#40000
0*
#40500
b11 1
b1001 +
b100 -
b11 /
b101000 ,
1*
#41000
0*
#41500
0)
b110 /
b1000 +
b110 1
b101001 ,
1*
#42000
0*
#42500
b1100 1
b111 +
b1100 /
b101010 ,
1*
#43000
0*
#43500
b11000 /
b110 +
b1000 1
b101011 ,
1*
#44000
0*
#44500
b0 1
b101 +
b10000 /
b101100 ,
1*
#45000
0*
#45500
b0 /
b100 +
b101101 ,
1*
#46000
0*
#46500
b11 +
b101110 ,
1*
#47000
0*
#47500
b10 +
b101111 ,
1*
#48000
0*
#48500
b1 1
b1 +
b1 /
1)
b110000 ,
1*
#49000
0*
#49500
1!
1(
0)
b10 /
b0 +
b10 1
b110001 ,
1*
#50000
0*
#50500
0!
0(
b100 1
b1001 +
b101 -
b100 /
b110010 ,
1*
#51000
0*
#51500
b1000 /
b1000 +
b1000 1
b110011 ,
1*
#52000
0*
#52500
b0 1
b111 +
b10000 /
b110100 ,
1*
#53000
0*
#53500
b0 /
b110 +
b110101 ,
1*
#54000
0*
#54500
b101 +
b110110 ,
1*
#55000
0*
#55500
b100 +
b110111 ,
1*
#56000
0*
#56500
b11 +
b111000 ,
1*
#57000
0*
#57500
b10 +
b111001 ,
1*
#58000
0*
#58500
b1 1
b1 +
b1 /
1)
b111010 ,
1*
#59000
0*
#59500
1!
1(
0)
b10 /
b0 +
b10 1
b111011 ,
1*
#60000
0*
#60500
0!
0(
b101 1
b1001 +
b110 -
b101 /
1)
b111100 ,
1*
#61000
0*
#61500
0)
b1010 /
b1000 +
b1010 1
b111101 ,
1*
#62000
0*
#62500
b100 1
b111 +
b10100 /
b111110 ,
1*
#63000
0*
#63500
b1000 /
b110 +
b1000 1
b111111 ,
1*
#64000
0*
#64500
b0 1
b101 +
b10000 /
b1000000 ,
1*
#65000
0*
#65500
b0 /
b100 +
b1000001 ,
1*
#66000
0*
#66500
b11 +
b1000010 ,
1*
#67000
0*
#67500
b10 +
b1000011 ,
1*
#68000
0*
#68500
b1 1
b1 +
b1 /
1)
b1000100 ,
1*
#69000
0*
#69500
b11 /
b0 +
b11 1
b1000101 ,
1*
#70000
0*
#70500
b110 1
b1001 +
b111 -
b110 /
0)
b1000110 ,
1*
#71000
0*
#71500
b1100 /
b1000 +
b1100 1
b1000111 ,
1*
#72000
0*
#72500
b1000 1
b111 +
b11000 /
b1001000 ,
1*
#73000
0*
#73500
b10000 /
b110 +
b0 1
b1001001 ,
1*
#74000
0*
#74500
b101 +
b0 /
b1001010 ,
1*
#75000
0*
#75500
b100 +
b1001011 ,
1*
#76000
0*
#76500
b11 +
b1001100 ,
1*
#77000
0*
#77500
b10 +
b1001101 ,
1*
#78000
0*
#78500
b1 1
b1 +
b1 /
1)
b1001110 ,
1*
#79000
0*
#79500
b11 /
b0 +
b11 1
b1001111 ,
1*
#80000
0*
#80500
b111 1
b1001 +
b1000 -
b111 /
b1010000 ,
1*
#81000
0*
#81500
0)
b1110 /
b1000 +
b1110 1
b1010001 ,
1*
#82000
0*
#82500
b1100 1
b111 +
b11100 /
b1010010 ,
1*
#83000
0*
#83500
b11000 /
b110 +
b1000 1
b1010011 ,
1*
#84000
0*
#84500
b0 1
b101 +
b10000 /
b1010100 ,
1*
#85000
0*
#85500
b0 /
b100 +
b1010101 ,
1*
#86000
0*
#86500
b11 +
b1010110 ,
1*
#87000
0*
#87500
b1 1
1)
b1 /
b10 +
b1010111 ,
1*
#88000
0*
#88500
1!
1(
b10 1
b1 +
b10 /
0)
b1011000 ,
1*
#89000
0*
#89500
0!
0(
b100 /
b0 +
b100 1
b1011001 ,
1*
#90000
0*
#90500
b1000 1
b1001 +
b1001 -
b1000 /
b1011010 ,
1*
#91000
0*
#91500
b10000 /
b1000 +
b0 1
b1011011 ,
1*
#92000
0*
#92500
b111 +
b0 /
b1011100 ,
1*
#93000
0*
#93500
b110 +
b1011101 ,
1*
#94000
0*
#94500
b101 +
b1011110 ,
1*
#95000
0*
#95500
b100 +
b1011111 ,
1*
#96000
0*
#96500
b11 +
b1100000 ,
1*
#97000
0*
#97500
b1 1
1)
b1 /
b10 +
b1100001 ,
1*
#98000
0*
#98500
1!
1(
b10 1
b1 +
b10 /
0)
b1100010 ,
1*
#99000
0*
#99500
0!
0(
b100 /
b0 +
b100 1
b1100011 ,
1*
#100000
0*
#100500
b1001 1
b1001 +
b1010 -
b1001 /
1)
b1100100 ,
1*
#101000
0*
#101500
1!
1(
0)
b10010 /
b1000 +
b10 1
b1100101 ,
1*
#102000
0*
#102500
0!
0(
b100 1
b111 +
b100 /
b1100110 ,
1*
#103000
0*
#103500
b1000 /
b110 +
b1000 1
b1100111 ,
1*
#104000
0*
#104500
b0 1
b101 +
b10000 /
b1101000 ,
1*
#105000
0*
#105500
b0 /
b100 +
b1101001 ,
1*
#106000
0*
#106500
b11 +
b1101010 ,
1*
#107000
0*
#107500
b1 1
1)
b1 /
b10 +
b1101011 ,
1*
#108000
0*
#108500
1!
1(
b10 1
b1 +
b10 /
0)
b1101100 ,
1*
#109000
0*
#109500
0!
0(
1)
b101 /
b0 +
b101 1
b1101101 ,
1*
#110000
0*
#110500
b1010 1
b1001 +
b1011 -
b1010 /
0)
b1101110 ,
1*
#111000
0*
#111500
b10100 /
b1000 +
b100 1
b1101111 ,
1*
#112000
0*
#112500
b1000 1
b111 +
b1000 /
b1110000 ,
1*
#113000
0*
#113500
b10000 /
b110 +
b0 1
b1110001 ,
1*
#114000
0*
#114500
b101 +
b0 /
b1110010 ,
1*
#115000
0*
#115500
b100 +
b1110011 ,
1*
#116000
0*
#116500
b11 +
b1110100 ,
1*
#117000
0*
#117500
b1 1
1)
b1 /
b10 +
b1110101 ,
1*
#118000
0*
#118500
1!
1(
b10 1
b1 +
b10 /
0)
b1110110 ,
1*
#119000
0*
#119500
0!
0(
1)
b101 /
b0 +
b101 1
b1110111 ,
1*
#120000
0*
#120500
b1011 1
b1001 +
b1100 -
b1011 /
b1111000 ,
1*
#121000
0*
#121500
0)
b10110 /
b1000 +
b110 1
b1111001 ,
1*
#122000
0*
#122500
b1100 1
b111 +
b1100 /
b1111010 ,
1*
#123000
0*
#123500
b11000 /
b110 +
b1000 1
b1111011 ,
1*
#124000
0*
#124500
b0 1
b101 +
b10000 /
b1111100 ,
1*
#125000
0*
#125500
b0 /
b100 +
b1111101 ,
1*
#126000
0*
#126500
b11 +
b1111110 ,
1*
#127000
0*
#127500
b1 1
1)
b1 /
b10 +
b1111111 ,
1*
#128000
0*
#128500
b11 1
b1 +
b11 /
b10000000 ,
1*
#129000
0*
#129500
0)
b110 /
b0 +
b110 1
b10000001 ,
1*
#130000
0*
#130500
b1100 1
b1001 +
b1101 -
b1100 /
b10000010 ,
1*
#131000
0*
#131500
b11000 /
b1000 +
b1000 1
b10000011 ,
1*
#132000
0*
#132500
b0 1
b111 +
b10000 /
b10000100 ,
1*
#133000
0*
#133500
b0 /
b110 +
b10000101 ,
1*
#134000
0*
#134500
b101 +
b10000110 ,
1*
#135000
0*
#135500
b100 +
b10000111 ,
1*
#136000
0*
#136500
b11 +
b10001000 ,
1*
#137000
0*
#137500
b1 1
1)
b1 /
b10 +
b10001001 ,
1*
#138000
0*
#138500
b11 1
b1 +
b11 /
b10001010 ,
1*
#139000
0*
#139500
0)
b110 /
b0 +
b110 1
b10001011 ,
1*
#140000
0*
#140500
b1101 1
b1001 +
b1110 -
b1101 /
1)
b10001100 ,
1*
#141000
0*
#141500
0)
b11010 /
b1000 +
b1010 1
b10001101 ,
1*
#142000
0*
#142500
b100 1
b111 +
b10100 /
b10001110 ,
1*
#143000
0*
#143500
b1000 /
b110 +
b1000 1
b10001111 ,
1*
#144000
0*
#144500
b0 1
b101 +
b10000 /
b10010000 ,
1*
#145000
0*
#145500
b0 /
b100 +
b10010001 ,
1*
#146000
0*
#146500
b11 +
b10010010 ,
1*
#147000
0*
#147500
b1 1
1)
b1 /
b10 +
b10010011 ,
1*
#148000
0*
#148500
b11 1
b1 +
b11 /
b10010100 ,
1*
#149000
0*
#149500
b111 /
b0 +
b111 1
b10010101 ,
1*
#150000
0*
#150500
b1110 1
b1001 +
b1111 -
b1110 /
0)
b10010110 ,
1*
#151000
0*
#151500
b11100 /
b1000 +
b1100 1
b10010111 ,
1*
#152000
0*
#152500
b1000 1
b111 +
b11000 /
b10011000 ,
1*
#153000
0*
#153500
b10000 /
b110 +
b0 1
b10011001 ,
1*
#154000
0*
#154500
b101 +
b0 /
b10011010 ,
1*
#155000
0*
#155500
b100 +
b10011011 ,
1*
#156000
0*
#156500
b11 +
b10011100 ,
1*
#157000
0*
#157500
b1 1
1)
b1 /
b10 +
b10011101 ,
1*
#158000
0*
#158500
b11 1
b1 +
b11 /
b10011110 ,
1*
#159000
0*
#159500
b111 /
b0 +
b111 1
b10011111 ,
1*
#160000
0*
#160500
b1111 1
b1001 +
b10000 -
b1111 /
b10100000 ,
1*
#161000
0*
#161500
b1110 1
0)
b11110 /
b1000 +
b10100001 ,
1*
#162000
0*
#162500
b1100 1
b111 +
b11100 /
b10100010 ,
1*
#163000
0*
#163500
b11000 /
b110 +
b1000 1
b10100011 ,
1*
#164000
0*
#164500
b0 1
b101 +
b10000 /
b10100100 ,
1*
#165000
0*
#165500
b0 /
b100 +
b10100101 ,
1*
#166000
0*
#166500
b1 1
b11 +
b1 /
1)
b10100110 ,
1*
#167000
0*
#167500
1!
1(
0)
b10 /
b10 +
b10 1
b10100111 ,
1*
#168000
0*
#168500
0!
0(
b100 1
b1 +
b100 /
b10101000 ,
1*
#169000
0*
#169500
b1000 /
b0 +
b1000 1
b10101001 ,
1*
#170000
0*
#170500
b0 1
b1001 +
b10001 -
b10000 /
b10101010 ,
1*
#171000
0*
#171500
b0 /
b1000 +
b10101011 ,
1*
#172000
0*
#172500
b111 +
b10101100 ,
1*
#173000
0*
#173500
b110 +
b10101101 ,
1*
#174000
0*
#174500
b101 +
b10101110 ,
1*
#175000
0*
#175500
b100 +
b10101111 ,
1*
#176000
0*
#176500
b1 1
b11 +
b1 /
1)
b10110000 ,
1*
#177000
0*
#177500
1!
1(
0)
b10 /
b10 +
b10 1
b10110001 ,
1*
#178000
0*
#178500
0!
0(
b100 1
b1 +
b100 /
b10110010 ,
1*
#179000
0*
#179500
b1000 /
b0 +
b1000 1
b10110011 ,
1*
#180000
0*
#180500
b1 1
b1001 +
b10010 -
b10001 /
1)
b10110100 ,
1*
#181000
0*
#181500
1!
1(
0)
b10 /
b1000 +
b10 1
b10110101 ,
1*
#182000
0*
#182500
0!
0(
b100 1
b111 +
b100 /
b10110110 ,
1*
#183000
0*
#183500
b1000 /
b110 +
b1000 1
b10110111 ,
1*
#184000
0*
#184500
b0 1
b101 +
b10000 /
b10111000 ,
1*
#185000
0*
#185500
b0 /
b100 +
b10111001 ,
1*
#186000
0*
#186500
b1 1
b11 +
b1 /
1)
b10111010 ,
1*
#187000
0*
#187500
1!
1(
0)
b10 /
b10 +
b10 1
b10111011 ,
1*
#188000
0*
#188500
0!
0(
b100 1
b1 +
b100 /
b10111100 ,
1*
#189000
0*
#189500
1)
b1001 /
b0 +
b1001 1
b10111101 ,
1*
#190000
0*
#190500
1!
1(
b10 1
b1001 +
b10011 -
b10010 /
0)
b10111110 ,
1*
#191000
0*
#191500
0!
0(
b100 /
b1000 +
b100 1
b10111111 ,
1*
#192000
0*
#192500
b1000 1
b111 +
b1000 /
b11000000 ,
1*
#193000
0*
#193500
b10000 /
b110 +
b0 1
b11000001 ,
1*
#194000
0*
#194500
b101 +
b0 /
b11000010 ,
1*
#195000
0*
#195500
b100 +
b11000011 ,
1*
#196000
0*
#196500
b1 1
b11 +
b1 /
1)
b11000100 ,
1*
#197000
0*
#197500
1!
1(
0)
b10 /
b10 +
b10 1
b11000101 ,
1*
#198000
0*
#198500
0!
0(
b100 1
b1 +
b100 /
b11000110 ,
1*
#199000
0*
#199500
1)
b1001 /
b0 +
b1001 1
b11000111 ,
1*
#200000
0*
#200500
b11 1
b1001 +
b10100 -
b10011 /
b11001000 ,
1*
#201000
0*
#201500
0)
b110 /
b1000 +
b110 1
b11001001 ,
1*
#202000
0*
#202500
b1100 1
b111 +
b1100 /
b11001010 ,
1*
#203000
0*
#203500
b11000 /
b110 +
b1000 1
b11001011 ,
1*
#204000
0*
#204500
b0 1
b101 +
b10000 /
b11001100 ,
1*
#205000
0*
#205500
b0 /
b100 +
b11001101 ,
1*
#206000
0*
#206500
b1 1
b11 +
b1 /
1)
b11001110 ,
1*
#207000
0*
#207500
1!
1(
0)
b10 /
b10 +
b10 1
b11001111 ,
1*
#208000
0*
#208500
0!
0(
b101 1
b1 +
b101 /
1)
b11010000 ,
1*
#209000
0*
#209500
0)
b1010 /
b0 +
b1010 1
b11010001 ,
1*
#210000
0*
#210500
b100 1
b1001 +
b10101 -
b10100 /
b11010010 ,
1*
#211000
0*
#211500
b1000 /
b1000 +
b1000 1
b11010011 ,
1*
#212000
0*
#212500
b0 1
b111 +
b10000 /
b11010100 ,
1*
#213000
0*
#213500
b0 /
b110 +
b11010101 ,
1*
#214000
0*
#214500
b101 +
b11010110 ,
1*
#215000
0*
#215500
b100 +
b11010111 ,
1*
#216000
0*
#216500
b1 1
b11 +
b1 /
1)
b11011000 ,
1*
#217000
0*
#217500
1!
1(
0)
b10 /
b10 +
b10 1
b11011001 ,
1*
#218000
0*
#218500
0!
0(
b101 1
b1 +
b101 /
1)
b11011010 ,
1*
#219000
0*
#219500
0)
b1010 /
b0 +
b1010 1
b11011011 ,
1*
#220000
0*
#220500
b101 1
b1001 +
b10110 -
b10101 /
1)
b11011100 ,
1*
#221000
0*
#221500
0)
b1010 /
b1000 +
b1010 1
b11011101 ,
1*
#222000
0*
#222500
b100 1
b111 +
b10100 /
b11011110 ,
1*
#223000
0*
#223500
b1000 /
b110 +
b1000 1
b11011111 ,
1*
#224000
0*
#224500
b0 1
b101 +
b10000 /
b11100000 ,
1*
#225000
0*
#225500
b0 /
b100 +
b11100001 ,
1*
#226000
0*
#226500
b1 1
b11 +
b1 /
1)
b11100010 ,
1*
#227000
0*
#227500
1!
1(
0)
b10 /
b10 +
b10 1
b11100011 ,
1*
#228000
0*
#228500
0!
0(
b101 1
b1 +
b101 /
1)
b11100100 ,
1*
#229000
0*
#229500
b1011 /
b0 +
b1011 1
b11100101 ,
1*
#230000
0*
#230500
b110 1
b1001 +
b10111 -
b10110 /
0)
b11100110 ,
1*
#231000
0*
#231500
b1100 /
b1000 +
b1100 1
b11100111 ,
1*
#232000
0*
#232500
b1000 1
b111 +
b11000 /
b11101000 ,
1*
#233000
0*
#233500
b10000 /
b110 +
b0 1
b11101001 ,
1*
#234000
0*
#234500
b101 +
b0 /
b11101010 ,
1*
#235000
0*
#235500
b100 +
b11101011 ,
1*
#236000
0*
#236500
b1 1
b11 +
b1 /
1)
b11101100 ,
1*
#237000
0*
#237500
1!
1(
0)
b10 /
b10 +
b10 1
b11101101 ,
1*
#238000
0*
#238500
0!
0(
b101 1
b1 +
b101 /
1)
b11101110 ,
1*
#239000
0*
#239500
b1011 /
b0 +
b1011 1
b11101111 ,
1*
#240000
0*
#240500
b111 1
b1001 +
b11000 -
b10111 /
b11110000 ,
1*
#241000
0*
#241500
0)
b1110 /
b1000 +
b1110 1
b11110001 ,
1*
#242000
0*
#242500
b1100 1
b111 +
b11100 /
b11110010 ,
1*
#243000
0*
#243500
b11000 /
b110 +
b1000 1
b11110011 ,
1*
#244000
0*
#244500
b0 1
b101 +
b10000 /
b11110100 ,
1*
#245000
0*
#245500
b0 /
b100 +
b11110101 ,
1*
#246000
0*
#246500
b1 1
b11 +
b1 /
1)
b11110110 ,
1*
#247000
0*
#247500
b11 /
b10 +
b11 1
b11110111 ,
1*
#248000
0*
#248500
b110 1
b1 +
b110 /
0)
b11111000 ,
1*
#249000
0*
#249500
b1100 /
b0 +
b1100 1
b11111001 ,
1*
#250000
0*
#250500
b1000 1
b1001 +
b11001 -
b11000 /
b11111010 ,
1*
#251000
0*
#251500
b10000 /
b1000 +
b0 1
b11111011 ,
1*
#252000
0*
#252500
b111 +
b0 /
b11111100 ,
1*
#253000
0*
#253500
b110 +
b11111101 ,
1*
#254000
0*
#254500
b101 +
b11111110 ,
1*
#255000
0*
#255500
b100 +
b11111111 ,
1*
#256000
0*
#256500
b1 1
b11 +
b1 /
1)
b100000000 ,
1*
#257000
0*
#257500
b11 /
b10 +
b11 1
b100000001 ,
1*
#258000
0*
#258500
b110 1
b1 +
b110 /
0)
b100000010 ,
1*
#259000
0*
#259500
b1100 /
b0 +
b1100 1
b100000011 ,
1*
#260000
0*
#260500
b1001 1
b1001 +
b11010 -
b11001 /
1)
b100000100 ,
1*
#261000
0*
#261500
1!
1(
0)
b10010 /
b1000 +
b10 1
b100000101 ,
1*
#262000
0*
#262500
0!
0(
b100 1
b111 +
b100 /
b100000110 ,
1*
#263000
0*
#263500
b1000 /
b110 +
b1000 1
b100000111 ,
1*
#264000
0*
#264500
b0 1
b101 +
b10000 /
b100001000 ,
1*
#265000
0*
#265500
b0 /
b100 +
b100001001 ,
1*
#266000
0*
#266500
b1 1
b11 +
b1 /
1)
b100001010 ,
1*
#267000
0*
#267500
b11 /
b10 +
b11 1
b100001011 ,
1*
#268000
0*
#268500
b110 1
b1 +
b110 /
0)
b100001100 ,
1*
#269000
0*
#269500
1)
b1101 /
b0 +
b1101 1
b100001101 ,
1*
#270000
0*
#270500
b1010 1
b1001 +
b11011 -
b11010 /
0)
b100001110 ,
1*
#271000
0*
#271500
b10100 /
b1000 +
b100 1
b100001111 ,
1*
#272000
0*
#272500
b1000 1
b111 +
b1000 /
b100010000 ,
1*
#273000
0*
#273500
b10000 /
b110 +
b0 1
b100010001 ,
1*
#274000
0*
#274500
b101 +
b0 /
b100010010 ,
1*
#275000
0*
#275500
b100 +
b100010011 ,
1*
#276000
0*
#276500
b1 1
b11 +
b1 /
1)
b100010100 ,
1*
#277000
0*
#277500
b11 /
b10 +
b11 1
b100010101 ,
1*
#278000
0*
#278500
b110 1
b1 +
b110 /
0)
b100010110 ,
1*
#279000
0*
#279500
1)
b1101 /
b0 +
b1101 1
b100010111 ,
1*
#280000
0*
#280500
b1011 1
b1001 +
b11100 -
b11011 /
b100011000 ,
1*
#281000
0*
#281500
0)
b10110 /
b1000 +
b110 1
b100011001 ,
1*
#282000
0*
#282500
b1100 1
b111 +
b1100 /
b100011010 ,
1*
#283000
0*
#283500
b11000 /
b110 +
b1000 1
b100011011 ,
1*
#284000
0*
#284500
b0 1
b101 +
b10000 /
b100011100 ,
1*
#285000
0*
#285500
b0 /
b100 +
b100011101 ,
1*
#286000
0*
#286500
b1 1
b11 +
b1 /
1)
b100011110 ,
1*
#287000
0*
#287500
b11 /
b10 +
b11 1
b100011111 ,
1*
#288000
0*
#288500
b111 1
b1 +
b111 /
b100100000 ,
1*
#289000
0*
#289500
0)
b1110 /
b0 +
b1110 1
b100100001 ,
1*
#290000
0*
#290500
b1100 1
b1001 +
b11101 -
b11100 /
b100100010 ,
1*
#291000
0*
#291500
b11000 /
b1000 +
b1000 1
b100100011 ,
1*
#292000
0*
#292500
b0 1
b111 +
b10000 /
b100100100 ,
1*
#293000
0*
#293500
b0 /
b110 +
b100100101 ,
1*
#294000
0*
#294500
b101 +
b100100110 ,
1*
#295000
0*
#295500
b100 +
b100100111 ,
1*
#296000
0*
#296500
b1 1
b11 +
b1 /
1)
b100101000 ,
1*
#297000
0*
#297500
b11 /
b10 +
b11 1
b100101001 ,
1*
#298000
0*
#298500
b111 1
b1 +
b111 /
b100101010 ,
1*
#299000
0*
#299500
0)
b1110 /
b0 +
b1110 1
b100101011 ,
1*
#300000
0*
#300500
b1101 1
b1001 +
b11110 -
b11101 /
1)
b100101100 ,
1*
#301000
0*
#301500
0)
b11010 /
b1000 +
b1010 1
b100101101 ,
1*
#302000
0*
#302500
b100 1
b111 +
b10100 /
b100101110 ,
1*
#303000
0*
#303500
b1000 /
b110 +
b1000 1
b100101111 ,
1*
#304000
0*
#304500
b0 1
b101 +
b10000 /
b100110000 ,
1*
#305000
0*
#305500
b0 /
b100 +
b100110001 ,
1*
#306000
0*
#306500
b1 1
b11 +
b1 /
1)
b100110010 ,
1*
#307000
0*
#307500
b11 /
b10 +
b11 1
b100110011 ,
1*
#308000
0*
#308500
b111 1
b1 +
b111 /
b100110100 ,
1*
#309000
0*
#309500
b1111 /
b0 +
b1111 1
b100110101 ,
1*
#310000
0*
#310500
b1110 1
b1001 +
b11111 -
b11110 /
0)
b100110110 ,
1*
#311000
0*
#311500
b11100 /
b1000 +
b1100 1
b100110111 ,
1*
#312000
0*
#312500
b1000 1
b111 +
b11000 /
b100111000 ,
1*
#313000
0*
#313500
b10000 /
b110 +
b0 1
b100111001 ,
1*
#314000
0*
#314500
b101 +
b0 /
b100111010 ,
1*
#315000
0*
#315500
b100 +
b100111011 ,
1*
#316000
0*
#316500
b1 1
b11 +
b1 /
1)
b100111100 ,
1*
#317000
0*
#317500
b11 /
b10 +
b11 1
b100111101 ,
1*
#318000
0*
#318500
b111 1
b1 +
b111 /
b100111110 ,
1*
#319000
0*
#319500
b1111 /
b0 +
b1111 1
b100111111 ,
1*
#320000
0*
#320500
b1001 +
b100000 -
b11111 /
b101000000 ,
1*
#321000
0*
#321500
b1110 1
0)
b11110 /
b1000 +
b101000001 ,
1*
#322000
0*
#322500
b1100 1
b111 +
b11100 /
b101000010 ,
1*
#323000
0*
#323500
b11000 /
b110 +
b1000 1
b101000011 ,
1*
#324000
0*
#324500
b0 1
b101 +
b10000 /
b101000100 ,
1*
#325000
0*
#325500
b1 1
1)
b1 /
b100 +
b101000101 ,
1*
#326000
0*
#326500
1!
1(
b10 1
b11 +
b10 /
0)
b101000110 ,
1*
#327000
0*
#327500
0!
0(
b100 /
b10 +
b100 1
b101000111 ,
1*
#328000
0*
#328500
b1000 1
b1 +
b1000 /
b101001000 ,
1*
#329000
0*
#329500
b10000 /
b0 +
b0 1
b101001001 ,
1*
#330000
0*
#330500
b1001 +
b100001 -
b0 /
b101001010 ,
1*
#331000
0*
#331500
b1000 +
b101001011 ,
1*
#332000
0*
#332500
b111 +
b101001100 ,
1*
#333000
0*
#333500
b110 +
b101001101 ,
1*
#334000
0*
#334500
b101 +
b101001110 ,
1*
#335000
0*
#335500
b1 1
1)
b1 /
b100 +
b101001111 ,
1*
#336000
0*
#336500
1!
1(
b10 1
b11 +
b10 /
0)
b101010000 ,
1*
#337000
0*
#337500
0!
0(
b100 /
b10 +
b100 1
b101010001 ,
1*
#338000
0*
#338500
b1000 1
b1 +
b1000 /
b101010010 ,
1*
#339000
0*
#339500
b10000 /
b0 +
b0 1
b101010011 ,
1*
#340000
0*
#340500
b1 1
b1001 +
b100010 -
b1 /
1)
b101010100 ,
1*
#341000
0*
#341500
1!
1(
0)
b10 /
b1000 +
b10 1
b101010101 ,
1*
#342000
0*
#342500
0!
0(
b100 1
b111 +
b100 /
b101010110 ,
1*
#343000
0*
#343500
b1000 /
b110 +
b1000 1
b101010111 ,
1*
#344000
0*
#344500
b0 1
b101 +
b10000 /
b101011000 ,
1*
#345000
0*
#345500
b1 1
1)
b1 /
b100 +
b101011001 ,
1*
#346000
0*
#346500
1!
1(
b10 1
b11 +
b10 /
0)
b101011010 ,
1*
