Lab3a/alu.v
module alu(alu_out, accum, data, opcode, zero, clk, reset);
input 		clk, reset;
input 	[7:0] 	accum, data;
input 	[2:0] 	opcode;
output 	reg [7:0] 	 alu_out;
output 		zero;

always@(posedge clk)
begin
    if(reset) alu_out <= 0;
    else
    begin
        case(opcode)
            3'b000: alu_out <= accum;
            3'b001: alu_out <= accum + data;
            3'b010: alu_out <= accum - data;
            3'b011: alu_out <= accum & data;
            3'b100: alu_out <= accum ^ data;
            3'b101: alu_out <= ~accum + 1;
            3'b110: alu_out <= accum*5 + (accum>>3);
            3'b111: alu_out <= (accum >= 8'd32) ? data : ~data;//1's complement 
            default:
            alu_out <= 8'b0;
        endcase
    end
end

assign zero = (accum  == 0 ) ? 1 : 0;//when accum equal 0, zero =1, else zero =0

endmodule

Lab5/alu_test.v
/*********************************************************************
 * Stimulus for the ALU design - Verilog Training Course
 *********************************************************************/
`timescale 1ns / 1ns
module alu_test;

reg [7:0] data, accum;
reg clk, reset;
reg [2:0] opcode;
wire zero;
wire [7:0] alu_out;

parameter cycle=20;//clk cycle = 20ns
parameter total_run=2;//check all function times
parameter func_run=10;//check one opcode how may times
parameter zero_run=1;//check zero output how may times//total run time *zero_run*8(opcode 3'd0~3'd7)

//golden signal or test signal
wire [7:0] opcode_0_golden;
wire [7:0] opcode_1_golden;
wire [7:0] opcode_2_golden;
wire [7:0] opcode_3_golden;
wire [7:0] opcode_4_golden;
wire [7:0] opcode_5_golden;
wire [7:0] opcode_6_golden;
wire [7:0] opcode_7_golden;
wire [7:0] opcode_other_golden;
wire zero_golden;
integer err_cnt;//error cnt
integer pass_cnt;//pass cnt
integer i;
integer j;
integer ze;//zero check only
//-------golden answer------
assign zero_golden = (accum === 8'd0) ? 1:0;
assign opcode_0_golden = accum;
assign opcode_1_golden = accum + data;
assign opcode_2_golden = accum - data;
assign opcode_3_golden = accum & data;
assign opcode_4_golden = accum ^ data;
assign opcode_5_golden = ~accum + 8'd1 ;
assign opcode_6_golden = accum*5 + accum/8;
assign opcode_7_golden = (accum>=8'd32)?data:~data;
assign opcode_other_golden = 8'd0;
//------------------------------

alu test_u1 (.clk(clk), .reset(reset), .data(data), .accum(accum), .opcode(opcode),
    .zero(zero), .alu_out(alu_out));
//clk
always #(cycle/2) clk = ~clk;

//simulation process
initial
begin
    $display("start simulation!!!");
    #30
    clk = 0;
    reset = 1;
    err_cnt = 0;
    pass_cnt = 0;
    i=0;
    #40
    reset = 0;
    for (j=0;j<total_run;j=j+1)begin
    //----------opcode 3'b000 check--------------
        for (i = 0; i < func_run;i = i + 1)begin
            @(negedge clk)begin
                opcode = 3'b000; 
                accum = $random%256; data = $random%256;
            end
            @(posedge clk)begin
                #(cycle/4)
                if (alu_out !== opcode_0_golden | zero_golden !== zero) begin
                    err_cnt = err_cnt + 1;
                    $display("err_cnt:%d",err_cnt);
                    $display("error at opcode=%b,accum=%b, data=%b", opcode, accum, data);
                    $display("expected output: alu_out=%b, zero=%d", opcode_0_golden, zero_golden);
                end
                else pass_cnt = pass_cnt + 1;
            end
        end
    //----------opcode 3'b001 check--------------   
        for (i = 0; i < func_run;i = i + 1) begin
            @(negedge clk)begin
                opcode = 3'b001; 
                accum = $random%256; data = $random%256;
            end
            @(posedge clk)begin
                #(cycle/4)
                if (alu_out !== opcode_1_golden | zero_golden !== zero) begin
                    err_cnt = err_cnt + 1;
                    $display("err_cnt:%d",err_cnt);
                    $display("error at opcode=%b,accum=%b, data=%b", opcode, accum, data);
                    $display("expected output: alu_out=%b, zero=%d", opcode_1_golden, zero_golden);
                end
                else pass_cnt = pass_cnt + 1;
            end
        end
    //----------opcode 3'b010 check--------------   
        for (i = 0; i < func_run;i = i + 1) begin
            @(negedge clk)begin
                opcode = 3'b010; 
                accum = $random%256; data = $random%256;
            end
            @(posedge clk)begin
                #(cycle/4)
                if (alu_out !== opcode_2_golden | zero_golden !== zero) begin
                    err_cnt = err_cnt + 1;
                    $display("err_cnt:%d",err_cnt);
                    $display("error at opcode=%b,accum=%b, data=%b", opcode, accum, data);
                    $display("expected output: alu_out=%b, zero=%d", opcode_2_golden, zero_golden);
                end
                else pass_cnt = pass_cnt + 1;
            end
        end
    //----------opcode 3'b011 check--------------
        for (i = 0; i < func_run;i = i + 1) begin
            @(negedge clk)begin 
                opcode = 3'b011;
                accum = $random%256; data = $random%256;
            end
            @(posedge clk)begin
            #(cycle/4)
            if (alu_out !== opcode_3_golden | zero_golden !== zero) begin
                err_cnt = err_cnt + 1;
                $display("err_cnt:%d",err_cnt);
                $display("error at opcode=%b,accum=%b, data=%b", opcode, accum, data);
                $display("expected output: alu_out=%b, zero=%d", opcode_3_golden, zero_golden);
            end
            else pass_cnt = pass_cnt + 1;
            end
        end
    //----------opcode 3'b100 check--------------
    opcode = 3'b100;
    for (i = 0; i < func_run;i = i + 1)
    begin
        @(negedge clk)begin 
        accum = $random%256; data = $random%256;
        end
        @(posedge clk)begin
        #1
        if (alu_out !== opcode_4_golden | zero_golden !== zero) begin
            err_cnt = err_cnt + 1;
            $display("err_cnt:%d",err_cnt);
            $display("error at opcode=%b,accum=%b, data=%b", opcode, accum, data);
            $display("expected output: alu_out=%b, zero=%d", opcode_4_golden, zero_golden);
        end
        else pass_cnt = pass_cnt + 1;
        end
    end
    //----------opcode 3'b101 check--------------
    opcode = 3'b101;
    for (i = 0; i < func_run;i = i + 1)
    begin
        @(negedge clk)begin 
        accum = $random%256; data = $random%256;
        end
        @(posedge clk)begin
        #1
        if (alu_out !== opcode_5_golden | zero_golden !== zero) begin
            err_cnt = err_cnt + 1;
            $display("err_cnt:%d",err_cnt);
            $display("error at opcode=%b,accum=%b, data=%b", opcode, accum, data);
            $display("expected output: alu_out=%b, zero=%d", opcode_5_golden, zero_golden);
        end
        else pass_cnt = pass_cnt + 1;
        end
    end
    //----------opcode 3'b110 check--------------
    opcode = 3'b110;
    for (i = 0; i < func_run;i = i + 1)
    begin
        @(negedge clk)begin 
        accum = $random%256; data = $random%256;
        end
        @(posedge clk)begin
        #1
        if (alu_out !== opcode_6_golden | zero_golden !== zero) begin
            err_cnt = err_cnt + 1;
            $display("err_cnt:%d",err_cnt);
            $display("error at opcode=%b,accum=%b, data=%b", opcode, accum, data);
            $display("expected output: alu_out=%b, zero=%d", opcode_6_golden, zero_golden);
        end
        else pass_cnt = pass_cnt + 1;
        end
    end
    //----------opcode 3'b111 check--------------
    opcode = 3'b111;
    for (i = 0; i < func_run;i = i + 1)
    begin
        @(negedge clk)begin 
        accum = $random%256; data = $random%256;
        end
        @(posedge clk)begin
        #1
        if (alu_out !== opcode_7_golden | zero_golden !== zero) begin
            err_cnt = err_cnt + 1;
            $display("err_cnt:%d",err_cnt);
            $display("error at opcode=%b,accum=%b, data=%b", opcode, accum, data);
            $display("expected output: alu_out=%b, zero=%d", opcode_7_golden, zero_golden);
        end
        else pass_cnt = pass_cnt + 1;
        end
    end
    //----------opcode 3'bxxx check--------------
    opcode = 3'bxxx;
    for (i = 0; i < func_run;i = i + 1)
    begin
        @(negedge clk)begin 
        accum = $random%256; data = $random%256;
        end
        @(posedge clk)begin
        #1
        if (alu_out !== opcode_other_golden | zero_golden !== zero) begin
            err_cnt = err_cnt + 1;
            $display("err_cnt:%d",err_cnt);
            $display("error at opcode=%b,accum=%b, data=%b", opcode, accum, data);
            $display("expected output: alu_out=%b, zero=%d", opcode_other_golden, zero_golden);
        end
        else pass_cnt = pass_cnt + 1;
        end
    end
    //----------opcode 3'bxzx check--------------
    opcode = 3'bxzx;
    for (i = 0; i < func_run;i = i + 1)
    begin
        @(negedge clk)begin 
        accum = $random%256; data = $random%256;
        end
        @(posedge clk)begin
        #1
        if (alu_out !== opcode_other_golden | zero_golden !== zero) begin
            err_cnt = err_cnt + 1;
            $display("err_cnt:%d",err_cnt);
            $display("error at opcode=%b,accum=%b, data=%b", opcode, accum, data);
            $display("expected output: alu_out=%b, zero=%d", opcode_other_golden, zero_golden);
        end
        else pass_cnt = pass_cnt + 1;
        end
    end
    //----------opcode 3'bxzx check--------------
    opcode = 3'bzzz;
    for (i = 0; i < func_run;i = i + 1)
    begin
        @(negedge clk)begin 
        accum = $random%256; data = $random%256;
        end
        @(posedge clk)begin
        #1
        if (alu_out !== opcode_other_golden | zero_golden !== zero) begin
            err_cnt = err_cnt + 1;
            $display("err_cnt:%d",err_cnt);
            $display("error at opcode=%b,accum=%b, data=%b", opcode, accum, data);
            $display("expected output: alu_out=%b, zero=%d", opcode_other_golden, zero_golden);
        end
        else pass_cnt = pass_cnt + 1;
        end
    end
    //----------zero check only--------------
    
    for (ze = 0; ze < 8*zero_run;ze = ze + 1)
    begin
    @(negedge clk)begin
        opcode = ze;
        accum = 0; data = $random%256;
    end
    @(posedge clk)begin
    #1
        if (zero_golden !== zero) begin
            err_cnt = err_cnt + 1;
            $display("zero check function!");
            $display("err_cnt:%d",err_cnt);
            $display("error at opcode=%b,accum=%b, data=%b", opcode, accum, data);
            $display("expected output: zero=%d", zero_golden);
        end
        else pass_cnt = pass_cnt + 1;
    end
    end
    //-----------------------------
    end
    //for end
    $display("simulation finish!!!");
    if (err_cnt > 0)
        $display("funcion fail, please check!");
    else
        $display("funcion pass, congratulations!");
    $display("Total error:%d", err_cnt);
    $display("Total pass:%d", pass_cnt);
    $display("pass rate(percentage):%d", (pass_cnt*100/(pass_cnt+err_cnt)));
    #200 $finish;
end
//dump waveform
initial 
begin
    //$fsdbDumpfile("fsm_wave.fsdb");
    //$fsdbDumpvars();
    $dumpfile("alu_wave.vcd");
    $dumpvars;
end

endmodule

Lab5/alu_wave.vcd
$date
	Sun Jan 28 23:29:55 2024
$end
$version
	Icarus Verilog
$end
$timescale
	1ns
$end
$scope module alu_test $end
$var wire 8 ! opcode_0_golden [7:0] $end
$var wire 8 " opcode_3_golden [7:0] $end
$var wire 8 # opcode_4_golden [7:0] $end
$var wire 8 $ opcode_other_golden [7:0] $end
$var wire 1 % zero_golden $end
$var wire 1 & zero $end
$var wire 8 ' opcode_7_golden [7:0] $end
$var wire 8 ( opcode_6_golden [7:0] $end
$var wire 8 ) opcode_5_golden [7:0] $end
$var wire 8 * opcode_2_golden [7:0] $end
$var wire 8 + opcode_1_golden [7:0] $end
$var wire 8 , alu_out [7:0] $end
$var parameter 32 - cycle $end
$var parameter 32 . func_run $end
$var parameter 32 / total_run $end
$var parameter 32 0 zero_run $end
$var reg 8 1 accum [7:0] $end
$var reg 1 2 clk $end
$var reg 8 3 data [7:0] $end
$var reg 3 4 opcode [2:0] $end
$var reg 1 5 reset $end
$var integer 32 6 err_cnt [31:0] $end
$var integer 32 7 i [31:0] $end
$var integer 32 8 j [31:0] $end
$var integer 32 9 pass_cnt [31:0] $end
$var integer 32 : ze [31:0] $end
$scope module test_u1 $end
$var wire 8 ; accum [7:0] $end
$var wire 1 2 clk $end
$var wire 8 < data [7:0] $end
$var wire 3 = opcode [2:0] $end
$var wire 1 5 reset $end
$var wire 1 & zero $end
$var reg 8 > alu_out [7:0] $end
$upscope $end
$upscope $end
$enddefinitions $end
$comment Show the parameter values. $end
$dumpall
b1 0
b10 /
b1010 .
b10100 -
$end
#0
$dumpvars
bx >
bx =
bx <
bx ;
bx :
bx 9
bx 8
bx 7
bx 6
x5
bx 4
bx 3
x2
bx 1
bx ,
bx +
bx *
bx )
bx (
bx '
x&
0%
b0 $
bx #
bx "
bx !
$end
#30
b0 ,
b0 >
b0 7
b0 9
b0 6
15
12
#40
02
#50
12
#60
02
#70
12
b0 8
05
#80
b10111000 (
b10000001 '
0&
b11011100 )
b10100101 #
b0 "
b10100101 +
b10100011 *
b10000001 3
b10000001 <
b100100 !
b100100 1
b100100 ;
b0 4
b0 =
02
#90
b100100 ,
b100100 >
12
#95
b1 7
b1 9
#100
b101110 (
b10011100 '
b11110111 )
b1101010 #
b1 "
b1100011 3
b1100011 <
b1101100 +
b10100110 *
b1001 !
b1001 1
b1001 ;
02
#110
b1001 ,
b1001 >
12
#115
b10 7
b10 9
#120
b1110010 '
b1000010 (
b11110011 )
b10000000 #
b1101 "
b10001101 3
b10001101 <
b10011010 +
b10000000 *
b1101 !
b1101 1
b1101 ;
02
#130
b1101 ,
b1101 >
12
#135
b11 7
b11 9
#140
b101 (
b10010 '
b10011011 )
b1110111 #
b0 "
b10010 3
b10010 <
b1110111 +
b1010011 *
b1100101 !
b1100101 1
b1100101 ;
02
#150
b1100101 ,
b1100101 >
12
#155
b100 7
b100 9
#160
b11110010 '
b11111111 )
b1100 #
b1 "
b1101 3
b1101 <
b1110 +
b11110100 *
b1 !
b1 1
b1 ;
02
#170
b1 ,
b1 >
12
#175
b101 7
b101 9
#180
b1011100 (
b111101 '
b10001010 )
b1001011 #
b110100 "
b111101 3
b111101 <
b10110011 +
b111001 *
b1110110 !
b1110110 1
b1110110 ;
02
#190
b1110110 ,
b1110110 >
12
#195
b110 7
b110 9
#200
b10001100 '
b10111110 (
b10011 )
b1100001 #
b10001100 "
b10001100 3
b10001100 <
b1111001 +
b1100001 *
b11101101 !
b11101101 1
b11101101 ;
02
#210
b11101101 ,
b11101101 >
12
#215
b111 7
b111 9
#220
b11000110 '
b11111100 (
b111 )
b111111 #
b11000000 "
b11000110 3
b11000110 <
b10111111 +
b110011 *
b11111001 !
b11111001 1
b11111001 ;
02
#230
b11111001 ,
b11111001 >
12
#235
b1000 7
b1000 9
#240
b10101010 '
b11110001 (
b111011 )
b1101111 #
b10000000 "
b10101010 3
b10101010 <
b1101111 +
b11011 *
b11000101 !
b11000101 1
b11000101 ;
02
#250
b11000101 ,
b11000101 >
12
#255
b1001 7
b1001 9
#260
b1110111 '
b10010101 (
b11011 )
b10010010 #
b1100101 "
b1110111 3
b1110111 <
b1011100 +
b1101110 *
b11100101 !
b11100101 1
b11100101 ;
02
#270
b11100101 ,
b11100101 >
12
#275
b0 7
b1010 9
#280
b1011100 (
b1110000 '
b11101110 )
b10011101 #
b10 "
b10001111 3
b10001111 <
b10100001 +
b10000011 *
b10010 !
b10010 1
b10010 ;
b1 4
b1 =
02
#290
b10100001 ,
b10100001 >
12
#295
b1 7
b1011 9
#300
b11011000 (
b11001110 '
b1110 )
b111100 #
b11000010 "
b11001110 3
b11001110 <
b11000000 +
b100100 *
b11110010 !
b11110010 1
b11110010 ;
02
#310
b11000000 ,
b11000000 >
12
#315
b10 7
b1100 9
#320
b11000101 '
b10100101 (
b11000 )
b101101 #
b11000000 "
b11000101 3
b11000101 <
b10101101 +
b100011 *
b11101000 !
b11101000 1
b11101000 ;
02
#330
b10101101 ,
b10101101 >
12
#335
b11 7
b1101 9
#340
b10111101 '
b11010111 (
b10100100 )
b11100001 #
b11100 "
b10111101 3
b10111101 <
b11001 +
b10011111 *
b1011100 !
b1011100 1
b1011100 ;
02
#350
b11001 ,
b11001 >
12
#355
b100 7
b1110 9
#360
b1100101 '
b11100110 (
b11010011 )
b1001000 #
b100101 "
b1100101 3
b1100101 <
b10010010 +
b11001000 *
b101101 !
b101101 1
b101101 ;
02
#370
b10010010 ,
b10010010 >
12
#375
b101 7
b1111 9
#380
b1010 '
b11111011 (
b10011101 )
b1101001 #
b10 "
b1010 3
b1010 <
b1101101 +
b1011001 *
b1100011 !
b1100011 1
b1100011 ;
02
#390
b1101101 ,
b1101101 >
12
#395
b110 7
b10000 9
#400
b100000 '
b10010000 (
b10000000 )
b10100000 #
b0 "
b100000 3
b100000 <
b10100000 +
b1100000 *
b10000000 !
b10000000 1
b10000000 ;
02
#410
b10100000 ,
b10100000 >
12
#415
b111 7
b10001 9
#420
b10011101 '
b1100111 (
b1010110 )
b110111 #
b10001000 "
b10011101 3
b10011101 <
b1000111 +
b1101 *
b10101010 !
b10101010 1
b10101010 ;
02
#430
b1000111 ,
b1000111 >
12
#435
b1000 7
b10010 9
#440
b10011 '
b0 (
b1101010 )
b10000101 #
b10010 "
b10011 3
b10011 <
b10101001 +
b10000011 *
b10010110 !
b10010110 1
b10010110 ;
02
#450
b10101001 ,
b10101001 >
12
#455
b1001 7
b10011 9
#460
b1000010 (
b10101100 '
b11110011 )
b1011110 #
b1 "
b1010011 3
b1010011 <
b1100000 +
b10111010 *
b1101 !
b1101 1
b1101 ;
02
#470
b1100000 ,
b1100000 >
12
#475
b0 7
b10100 9
#480
b100100 (
b11010101 '
b10010101 )
b10111110 #
b1000001 "
b11010101 3
b11010101 <
b1000000 +
b10010110 *
b1101011 !
b1101011 1
b1101011 ;
b10 4
b10 =
02
#490
b10010110 ,
b10010110 >
12
#495
b1 7
b10101 9
#500
b1010 (
b1010001 '
b11111110 )
b10101100 #
b10 "
b10101110 3
b10101110 <
b10110000 +
b1010100 *
b10 !
b10 1
b10 ;
02
#510
b1010100 ,
b1010100 >
12
#515
b10 7
b10110 9
#520
b110000 '
b10010100 (
b11100011 )
b11010010 #
b1101 "
b11001111 3
b11001111 <
b11101100 +
b1001110 *
b11101 !
b11101 1
b11101 ;
02
#530
b1001110 ,
b1001110 >
12
#535
b11 7
b10111 9
#540
b10110011 (
b1010 '
b11011101 )
b101001 #
b10 "
b1010 3
b1010 <
b101101 +
b11001 *
b100011 !
b100011 1
b100011 ;
02
#550
b11001 ,
b11001 >
12
#555
b100 7
b11000 9
#560
b111100 '
b1011 (
b110110 )
b11110110 #
b1000 "
b111100 3
b111100 <
b110 +
b10001110 *
b11001010 !
b11001010 1
b11001010 ;
02
#570
b10001110 ,
b10001110 >
12
#575
b101 7
b11001 9
#580
b10001010 '
b11011000 (
b1110 )
b1111000 #
b10000010 "
b10001010 3
b10001010 <
b1111100 +
b1101000 *
b11110010 !
b11110010 1
b11110010 ;
02
#590
b1101000 ,
b1101000 >
12
#595
b110 7
b11010 9
#600
b11011000 '
b1001101 (
b10111111 )
b10011001 #
b1000000 "
b11011000 3
b11011000 <
b11001 +
b1101001 *
b1000001 !
b1000001 1
b1000001 ;
02
#610
b1101001 ,
b1101001 >
12
#615
b111 7
b11011 9
#620
b10001001 '
b1100111 (
b10001000 )
b11110001 #
b1000 "
b10001001 3
b10001001 <
b1 +
b11101111 *
b1111000 !
b1111000 1
b1111000 ;
02
#630
b11101111 ,
b11101111 >
12
#635
b1000 7
b11100 9
#640
b10110110 '
b10110100 (
b10101 )
b1011101 #
b10100010 "
b10110110 3
b10110110 <
b10100001 +
b110101 *
b11101011 !
b11101011 1
b11101011 ;
02
#650
b110101 ,
b110101 >
12
#655
b1001 7
b11101 9
#660
b10101110 '
b11110110 (
b111010 )
b1101000 #
b10000110 "
b10101110 3
b10101110 <
b1110100 +
b11000 *
b11000110 !
b11000110 1
b11000110 ;
02
#670
b11000 ,
b11000 >
12
#675
b0 7
b11110 9
#680
b101010 '
b11000011 (
b1000100 )
b10010110 #
b101000 "
b101010 3
b101010 <
b11100110 +
b10010010 *
b10111100 !
b10111100 1
b10111100 ;
b11 4
b11 =
02
#690
b0 ,
b0 >
12
#695
b1 7
b1 6
#700
b111000 (
b10001110 '
b11110101 )
b1111010 #
b1 "
b1110001 3
b1110001 <
b1111100 +
b10011010 *
b1011 !
b1011 1
b1011 ;
02
#710
12
#715
b10 7
b10 6
#720
b10101001 (
b1001111 '
b1111011 )
b11001010 #
b101 "
b1001111 3
b1001111 <
b11010100 +
b110110 *
b10000101 !
b10000101 1
b10000101 ;
02
#730
12
#735
b11 7
b11 6
#740
b111010 '
b101110 (
b11000101 )
b1 #
b111010 "
b111010 3
b111010 <
b1110101 +
b1 *
b111011 !
b111011 1
b111011 ;
02
#750
12
#755
b100 7
b100 6
#760
b10101 '
b10000101 (
b10000010 )
b1101011 #
b10100 "
b10101 3
b10101 <
b10010011 +
b1101001 *
b1111110 !
b1111110 1
b1111110 ;
02
#770
12
#775
b101 7
b101 6
#780
b11011001 '
b11010011 (
b1111 )
b101000 #
b11010001 "
b11011001 3
b11011001 <
b11001010 +
b11000 *
b11110001 !
b11110001 1
b11110001 ;
02
#790
12
#795
b110 7
b110 6
#800
b1001100 '
b11110110 (
b10011110 )
b101110 #
b1000000 "
b1001100 3
b1001100 <
b10101110 +
b10110 *
b1100010 !
b1100010 1
b1100010 ;
02
#810
12
#815
b111 7
b111 6
#820
b10001111 '
b101110 (
b1100001 )
b10000 #
b10001111 "
b10001111 3
b10001111 <
b101110 +
b10000 *
b10011111 !
b10011111 1
b10011111 ;
02
#830
12
#835
b1000 7
b1000 6
#840
b10110111 '
b11110111 (
b1000 )
b1001111 #
b10110000 "
b10110111 3
b10110111 <
b10101111 +
b1000001 *
b11111000 !
b11111000 1
b11111000 ;
02
#850
12
#855
b1001 7
b1001 6
#860
b1011100 '
b101110 (
b1100001 )
b11000011 #
b11100 "
b1011100 3
b1011100 <
b11111011 +
b1000011 *
b10011111 !
b10011111 1
b10011111 ;
02
#870
12
#875
b100 4
b100 =
b0 7
b1010 6
#880
b10001001 '
b11010010 (
b10100101 )
b11010010 #
b1001 "
b10001001 3
b10001001 <
b11100100 +
b11010010 *
b1011011 !
b1011011 1
b1011011 ;
02
#890
b11010010 ,
b11010010 >
12
#891
b1 7
b11111 9
#900
b11010000 '
b1110110 (
b10110111 )
b10011001 #
b1000000 "
b11010000 3
b11010000 <
b11001 +
b1111001 *
b1001001 !
b1001001 1
b1001001 ;
02
#910
b10011001 ,
b10011001 >
12
#911
b10 7
b100000 9
#920
b1010001 '
b1001101 (
b101001 )
b10000110 #
b1010001 "
b1010001 3
b1010001 <
b101000 +
b10000110 *
b11010111 !
b11010111 1
b11010111 ;
02
#930
b10000110 ,
b10000110 >
12
#931
b11 7
b100001 9
#940
b1100 '
b0 (
b1101010 )
b10011010 #
b100 "
b1100 3
b1100 <
b10100010 +
b10001010 *
b10010110 !
b10010110 1
b10010110 ;
02
#950
b10011010 ,
b10011010 >
12
#951
b100 7
b100010 9
#960
b11001000 '
b11100010 (
b111110 )
b1010 #
b11000000 "
b11001000 3
b11001000 <
b10001010 +
b11111010 *
b11000010 !
b11000010 1
b11000010 ;
02
#970
b1010 ,
b1010 >
12
#971
b101 7
b100011 9
#980
b111101 '
b1100001 (
b10001001 )
b1001010 #
b110101 "
b111101 3
b111101 <
b10110100 +
b111010 *
b1110111 !
b1110111 1
b1110111 ;
02
#990
b1001010 ,
b1001010 >
12
#991
b110 7
b100100 9
#1000
b1011100 (
b10000001 '
b11101110 )
b1101100 #
b10010 "
b1111110 3
b1111110 <
b10010000 +
b10010100 *
b10010 !
b10010 1
b10010 ;
02
#1010
b1101100 ,
b1101100 >
12
#1011
b111 7
b100101 9
#1020
b101110 (
b111001 '
b10010011 )
b1010100 #
b101001 "
b111001 3
b111001 <
b10100110 +
b110100 *
b1101101 !
b1101101 1
b1101101 ;
02
#1030
b1010100 ,
b1010100 >
12
#1031
b1000 7
b100110 9
#1040
b10011110 (
b101100 '
b11100001 )
b11001100 #
b10011 "
b11010011 3
b11010011 <
b11110010 +
b1001100 *
b11111 !
b11111 1
b11111 ;
02
#1050
b11001100 ,
b11001100 >
12
#1051
b1001 7
b100111 9
#1060
b10101001 (
b1111000 '
b1111011 )
b11111101 #
b0 "
b1111000 3
b1111000 <
b11111101 +
b1101 *
b10000101 !
b10000101 1
b10000101 ;
02
#1070
b11111101 ,
b11111101 >
12
#1071
b101 4
b101 =
b0 7
b101000 9
#1080
b1001001 '
b11010010 (
b10100101 )
b10010 #
b1001001 "
b1001001 3
b1001001 <
b10100100 +
b10010 *
b1011011 !
b1011011 1
b1011011 ;
02
#1090
b10100101 ,
b10100101 >
12
#1091
b1 7
b101001 9
#1100
b101010 '
b1000010 (
b11000001 )
b10101 #
b101010 "
b101010 3
b101010 <
b1101001 +
b10101 *
b111111 !
b111111 1
b111111 ;
02
#1110
b11000001 ,
b11000001 >
12
#1111
b10 7
b101010 9
#1120
b10000110 '
b11000011 (
b10101000 )
b11011110 #
b0 "
b10000110 3
b10000110 <
b11011110 +
b11010010 *
b1011000 !
b1011000 1
b1011000 ;
02
#1130
b10101000 ,
b10101000 >
12
#1131
b11 7
b101011 9
#1140
b10011100 '
b11010111 (
b1110010 )
b10010 #
b10001100 "
b10011100 3
b10011100 <
b101010 +
b11110010 *
b10001110 !
b10001110 1
b10001110 ;
02
#1150
b1110010 ,
b1110010 >
12
#1151
b100 7
b101100 9
#1160
b100110 '
b1 (
b110 )
b11011100 #
b100010 "
b100110 3
b100110 <
b100000 +
b11010100 *
b11111010 !
b11111010 1
b11111010 ;
02
#1170
b110 ,
b110 >
12
#1171
b101 7
b101101 9
#1180
b10100011 '
b1001101 (
b10001101 )
b11010000 #
b100011 "
b10100011 3
b10100011 <
b10110 +
b11010000 *
b1110011 !
b1110011 1
b1110011 ;
02
#1190
b10001101 ,
b10001101 >
12
#1191
b110 7
b101110 9
#1200
b10110011 '
b11110000 (
b11010001 )
b10011100 #
b10110011 3
b10110011 <
b11100010 +
b1111100 *
b101111 !
b101111 1
b101111 ;
02
#1210
b11010001 ,
b11010001 >
12
#1211
b111 7
b101111 9
#1220
b1000100 '
b11100110 (
b10100001 )
b11011 #
b1000100 "
b1000100 3
b1000100 <
b10100011 +
b11011 *
b1011111 !
b1011111 1
b1011111 ;
02
#1230
b10100001 ,
b10100001 >
12
#1231
b1000 7
b110000 9
#1240
b11001011 '
b11110001 (
b1001 )
b111100 #
b11000011 "
b11001011 3
b11001011 <
b11000010 +
b101100 *
b11110111 !
b11110111 1
b11110111 ;
02
#1250
b1001 ,
b1001 >
12
#1251
b1001 7
b110001 9
#1260
b1011010 '
b10011010 (
b11010 )
b10111100 #
b1000010 "
b1011010 3
b1011010 <
b1000000 +
b10001100 *
b11100110 !
b11100110 1
b11100110 ;
02
#1270
b11010 ,
b11010 >
12
#1271
b110 4
b110 =
b0 7
b110010 9
#1280
b11101101 '
b11010010 (
b11010111 )
b11000100 #
b101001 "
b11101101 3
b11101101 <
b10110 +
b111100 *
b101001 !
b101001 1
b101001 ;
02
#1290
b11010010 ,
b11010010 >
12
#1291
b1 7
b110011 9
#1300
b1100101 '
b1011101 (
b100110 )
b10111111 #
b1000000 "
b1100101 3
b1100101 <
b111111 +
b1110101 *
b11011010 !
b11011010 1
b11011010 ;
02
#1310
b1011101 ,
b1011101 >
12
#1311
b10 7
b110100 9
#1320
b11011111 '
b10011111 (
b1001011 )
b1101010 #
b10010101 "
b11011111 3
b11011111 <
b10010100 +
b11010110 *
b10110101 !
b10110101 1
b10110101 ;
02
#1330
b10011111 ,
b10011111 >
12
#1331
b11 7
b110101 9
#1340
b1000100 '
b1101100 (
b10000111 )
b111101 #
b1000000 "
b1000100 3
b1000100 <
b10111101 +
b110101 *
b1111001 !
b1111001 1
b1111001 ;
02
#1350
b1101100 ,
b1101100 >
12
#1351
b100 7
b110110 9
#1360
b101010 '
b101010 (
b110000 )
b11111010 #
b0 "
b101010 3
b101010 <
b11111010 +
b10100110 *
b11010000 !
b11010000 1
b11010000 ;
02
#1370
b101010 ,
b101010 >
12
#1371
b101 7
b110111 9
#1380
b1110 '
b1101100 (
b1010101 )
b10100101 #
b1010 "
b1110 3
b1110 <
b10111001 +
b10011101 *
b10101011 !
b10101011 1
b10101011 ;
02
#1390
b1101100 ,
b1101100 >
12
#1391
b110 7
b111000 9
#1400
b10011010 '
b1100111 (
b100100 )
b1000110 #
b10011000 "
b10011010 3
b10011010 <
b1110110 +
b1000010 *
b11011100 !
b11011100 1
b11011100 ;
02
#1410
b1100111 ,
b1100111 >
12
#1411
b111 7
b111001 9
#1420
b11000011 '
b10000 (
b11 )
b111110 #
b11000001 "
b11000011 3
b11000011 <
b11000000 +
b111010 *
b11111101 !
b11111101 1
b11111101 ;
02
#1430
b10000 ,
b10000 >
12
#1431
b1000 7
b111010 9
#1440
b1001110 '
b10111000 (
b10101010 )
b11000 #
b1000110 "
b1001110 3
b1001110 <
b10100100 +
b1000 *
b1010110 !
b1010110 1
b1010110 ;
02
#1450
b10111000 ,
b10111000 >
12
#1451
b1001 7
b111011 9
#1460
b1010 '
b1111 (
b10011001 )
b1101101 #
b10 "
b1010 3
b1010 <
b1110001 +
b1011101 *
b1100111 !
b1100111 1
b1100111 ;
02
#1470
b1111 ,
b1111 >
12
#1471
b111 4
b111 =
b0 7
b111100 9
#1480
b111000 '
b10100100 (
b1001010 )
b10001110 #
b110000 "
b111000 3
b111000 <
b11101110 +
b1111110 *
b10110110 !
b10110110 1
b10110110 ;
02
#1490
b111000 ,
b111000 >
12
#1491
b1 7
b111101 9
#1500
b10111000 '
b1101100 (
b10000111 )
b11000001 #
b111000 "
b10111000 3
b10111000 <
b110001 +
b11000001 *
b1111001 !
b1111001 1
b1111001 ;
02
#1510
b10111000 ,
b10111000 >
12
#1511
b10 7
b111110 9
#1520
b10010011 '
b11110110 (
b1101100 )
b111 #
b10010000 "
b10010011 3
b10010011 <
b100111 +
b1 *
b10010100 !
b10010100 1
b10010100 ;
02
#1530
b10010011 ,
b10010011 >
12
#1531
b11 7
b111111 9
#1540
b10100 (
b10100110 '
b11111100 )
b1011101 #
b0 "
b1011001 3
b1011001 <
b1011101 +
b10101011 *
b100 !
b100 1
b100 ;
02
#1550
b10100110 ,
b10100110 >
12
#1551
b100 7
b1000000 9
#1560
b1100010 (
b1001101 '
b100101 )
b10010110 #
b1001001 "
b1001101 3
b1001101 <
b101000 +
b10001110 *
b11011011 !
b11011011 1
b11011011 ;
02
#1570
b1001101 ,
b1001101 >
12
#1571
b101 7
b1000001 9
#1580
b1101101 '
b1011000 (
b100111 )
b10110100 #
b1101101 3
b1101101 <
b1000110 +
b1101100 *
b11011001 !
b11011001 1
b11011001 ;
02
#1590
b1101101 ,
b1101101 >
12
#1591
b110 7
b1000010 9
